ultimaterag/__init__.py
ultimaterag/cli.py
ultimaterag/server.py
ultimaterag/API/v1/router.py
ultimaterag/API/v1/endpoints/agent.py
ultimaterag/API/v1/endpoints/chat.py
ultimaterag/API/v1/endpoints/ingest.py
ultimaterag/API/v1/endpoints/memory.py
ultimaterag/Database/Connection.py
ultimaterag/Database/DataAdding.py
ultimaterag/Database/vectorSearch.py
ultimaterag/LLM/connection.py
ultimaterag/LLM/embeddings.py
ultimaterag/Prompts/SystemPrompt.py
ultimaterag/Prompts/manager.py
ultimaterag/config/settings.py
ultimaterag/core/container.py
ultimaterag/core/memory.py
ultimaterag/core/rag_engine.py
ultimaterag/core/vector_store.py
ultimaterag/core/vector_db/base.py
ultimaterag/core/vector_db/chroma.py
ultimaterag/core/vector_db/postgres.py
ultimaterag/core/workflows/chains.py
ultimaterag/core/workflows/engine.py
ultimaterag/utils/Response_Helper.py
ultimaterag/utils/Response_Helper_Model.py
ultimaterag-0.1.1.dist-info/licenses/LICENSE
ultimaterag-0.1.1.dist-info/METADATA
ultimaterag-0.1.1.dist-info/WHEEL
ultimaterag-0.1.1.dist-info/entry_points.txt
ultimaterag-0.1.1.dist-info/top_level.txt
ultimaterag-0.1.1.dist-info/RECORD
