Metadata-Version: 2.4
Name: ultimaterag
Version: 0.1.1
Summary: A modular, production-ready Retrieval-Augmented Generation (RAG) platform with multi-vector database support
Author-email: Matrixxboy <matrix.utsav.lankapati@gmail.com>
License: MIT
Project-URL: Homepage, https://theultimaterag.vercel.app/
Project-URL: Documentation, https://theultimaterag.vercel.app/docs
Project-URL: Source, https://github.com/Matrixxboy/TheUnltimateRAG
Project-URL: Issues, https://github.com/Matrixxboy/TheUnltimateRAG/issues
Keywords: rag,llm,ai,fastapi,langchain,vector-database,retrieval-augmented-generation
Classifier: Development Status :: 3 - Alpha
Classifier: Intended Audience :: Developers
Classifier: Programming Language :: Python :: 3
Classifier: Programming Language :: Python :: 3.10
Classifier: License :: OSI Approved :: MIT License
Classifier: Operating System :: OS Independent
Classifier: Framework :: FastAPI
Classifier: Topic :: Scientific/Engineering :: Artificial Intelligence
Requires-Python: >=3.10
License-File: LICENSE
Requires-Dist: fastapi>=0.110.0
Requires-Dist: uvicorn>=0.27.0
Requires-Dist: python-dotenv>=1.0.1
Requires-Dist: httpx>=0.27.0
Requires-Dist: python-multipart>=0.0.9
Requires-Dist: pydantic>=2.6.0
Requires-Dist: pydantic-settings>=2.2.0
Requires-Dist: langchain>=0.1.10
Requires-Dist: langchain-core>=0.1.28
Requires-Dist: langchain-community>=0.0.25
Requires-Dist: langchain-openai>=0.0.8
Requires-Dist: langchain-text-splitters>=0.0.1
Requires-Dist: chromadb>=0.4.24
Requires-Dist: pgvector>=0.2.5
Requires-Dist: psycopg2-binary>=2.9.9
Requires-Dist: redis>=5.0.0
Requires-Dist: openai>=1.13.0
Requires-Dist: tiktoken>=0.6.0
Requires-Dist: pypdf>=4.0.0
Requires-Dist: scikit-learn>=1.4.0
Requires-Dist: typer>=0.9.0
Provides-Extra: dev
Requires-Dist: pytest>=8.0.0; extra == "dev"
Requires-Dist: black; extra == "dev"
Requires-Dist: ruff; extra == "dev"
Requires-Dist: mypy; extra == "dev"
Dynamic: license-file
